<?xml version="1.0" encoding="UTF-8"?>
<GenRun Id="impl_1" LaunchPart="xc7a100tcsg324-1" LaunchTime="1644513325">
  <File Type="BITSTR-BMM" Name="temp_top_bd.bmm"/>
  <File Type="OPT-METHODOLOGY-DRC" Name="temp_top_methodology_drc_opted.rpt"/>
  <File Type="INIT-TIMING" Name="temp_top_timing_summary_init.rpt"/>
  <File Type="ROUTE-PWR" Name="temp_top_power_routed.rpt"/>
  <File Type="PA-TCL" Name="temp_top.tcl"/>
  <File Type="OPT-TIMING" Name="temp_top_timing_summary_opted.rpt"/>
  <File Type="OPT-DCP" Name="temp_top_opt.dcp"/>
  <File Type="ROUTE-PWR-SUM" Name="temp_top_power_summary_routed.pb"/>
  <File Type="REPORTS-TCL" Name="temp_top_reports.tcl"/>
  <File Type="OPT-DRC" Name="temp_top_drc_opted.rpt"/>
  <File Type="OPT-HWDEF" Name="temp_top.hwdef"/>
  <File Type="PWROPT-DCP" Name="temp_top_pwropt.dcp"/>
  <File Type="PWROPT-DRC" Name="temp_top_drc_pwropted.rpt"/>
  <File Type="PWROPT-TIMING" Name="temp_top_timing_summary_pwropted.rpt"/>
  <File Type="PLACE-DCP" Name="temp_top_placed.dcp"/>
  <File Type="PLACE-IO" Name="temp_top_io_placed.rpt"/>
  <File Type="PLACE-CLK" Name="temp_top_clock_utilization_placed.rpt"/>
  <File Type="PLACE-UTIL" Name="temp_top_utilization_placed.rpt"/>
  <File Type="PLACE-UTIL-PB" Name="temp_top_utilization_placed.pb"/>
  <File Type="PLACE-CTRL" Name="temp_top_control_sets_placed.rpt"/>
  <File Type="PLACE-SIMILARITY" Name="temp_top_incremental_reuse_placed.rpt"/>
  <File Type="PLACE-PRE-SIMILARITY" Name="temp_top_incremental_reuse_pre_placed.rpt"/>
  <File Type="PLACE-TIMING" Name="temp_top_timing_summary_placed.rpt"/>
  <File Type="POSTPLACE-PWROPT-DCP" Name="temp_top_postplace_pwropt.dcp"/>
  <File Type="BG-BIN" Name="temp_top.bin"/>
  <File Type="POSTPLACE-PWROPT-TIMING" Name="temp_top_timing_summary_postplace_pwropted.rpt"/>
  <File Type="PHYSOPT-DCP" Name="temp_top_physopt.dcp"/>
  <File Type="PHYSOPT-DRC" Name="temp_top_drc_physopted.rpt"/>
  <File Type="BITSTR-MSK" Name="temp_top.msk"/>
  <File Type="PHYSOPT-TIMING" Name="temp_top_timing_summary_physopted.rpt"/>
  <File Type="ROUTE-ERROR-DCP" Name="temp_top_routed_error.dcp"/>
  <File Type="ROUTE-DCP" Name="temp_top_routed.dcp"/>
  <File Type="ROUTE-BLACKBOX-DCP" Name="temp_top_routed_bb.dcp"/>
  <File Type="ROUTE-DRC" Name="temp_top_drc_routed.rpt"/>
  <File Type="ROUTE-DRC-PB" Name="temp_top_drc_routed.pb"/>
  <File Type="ROUTE-DRC-RPX" Name="temp_top_drc_routed.rpx"/>
  <File Type="BITSTR-MMI" Name="temp_top.mmi"/>
  <File Type="ROUTE-METHODOLOGY-DRC" Name="temp_top_methodology_drc_routed.rpt"/>
  <File Type="ROUTE-METHODOLOGY-DRC-RPX" Name="temp_top_methodology_drc_routed.rpx"/>
  <File Type="ROUTE-METHODOLOGY-DRC-PB" Name="temp_top_methodology_drc_routed.pb"/>
  <File Type="ROUTE-PWR-RPX" Name="temp_top_power_routed.rpx"/>
  <File Type="ROUTE-STATUS" Name="temp_top_route_status.rpt"/>
  <File Type="ROUTE-STATUS-PB" Name="temp_top_route_status.pb"/>
  <File Type="ROUTE-TIMINGSUMMARY" Name="temp_top_timing_summary_routed.rpt"/>
  <File Type="ROUTE-TIMING-PB" Name="temp_top_timing_summary_routed.pb"/>
  <File Type="ROUTE-TIMING-RPX" Name="temp_top_timing_summary_routed.rpx"/>
  <File Type="ROUTE-SIMILARITY" Name="temp_top_incremental_reuse_routed.rpt"/>
  <File Type="ROUTE-CLK" Name="temp_top_clock_utilization_routed.rpt"/>
  <File Type="ROUTE-BUS-SKEW" Name="temp_top_bus_skew_routed.rpt"/>
  <File Type="ROUTE-BUS-SKEW-PB" Name="temp_top_bus_skew_routed.pb"/>
  <File Type="ROUTE-BUS-SKEW-RPX" Name="temp_top_bus_skew_routed.rpx"/>
  <File Type="POSTROUTE-PHYSOPT-DCP" Name="temp_top_postroute_physopt.dcp"/>
  <File Type="POSTROUTE-PHYSOPT-BLACKBOX-DCP" Name="temp_top_postroute_physopt_bb.dcp"/>
  <File Type="POSTROUTE-PHYSOPT-TIMING" Name="temp_top_timing_summary_postroute_physopted.rpt"/>
  <File Type="POSTROUTE-PHYSOPT-TIMING-PB" Name="temp_top_timing_summary_postroute_physopted.pb"/>
  <File Type="POSTROUTE-PHYSOPT-TIMING-RPX" Name="temp_top_timing_summary_postroute_physopted.rpx"/>
  <File Type="POSTROUTE-PHYSOPT-BUS-SKEW" Name="temp_top_bus_skew_postroute_physopted.rpt"/>
  <File Type="POSTROUTE-PHYSOPT-BUS-SKEW-PB" Name="temp_top_bus_skew_postroute_physopted.pb"/>
  <File Type="BG-BIT" Name="temp_top.bit"/>
  <File Type="POSTROUTE-PHYSOPT-BUS-SKEW-RPX" Name="temp_top_bus_skew_postroute_physopted.rpx"/>
  <File Type="BITSTR-RBT" Name="temp_top.rbt"/>
  <File Type="BITSTR-NKY" Name="temp_top.nky"/>
  <File Type="PDI-FILE" Name="temp_top.pdi"/>
  <File Type="RCFI_FILE" Name="temp_top.rcfi"/>
  <File Type="CFI_FILE" Name="temp_top.cfi"/>
  <File Type="RNPI_FILE" Name="temp_top.rnpi"/>
  <File Type="NPI_FILE" Name="temp_top.npi"/>
  <File Type="RBD_FILE" Name="temp_top.rbd"/>
  <File Type="BITSTR-LTX" Name="debug_nets.ltx"/>
  <File Type="BITSTR-LTX" Name="temp_top.ltx"/>
  <File Type="BITSTR-SYSDEF" Name="temp_top.sysdef"/>
  <File Type="BG-BGN" Name="temp_top.bgn"/>
  <File Type="BG-DRC" Name="temp_top.drc"/>
  <File Type="RDI-RDI" Name="temp_top.vdi"/>
  <File Type="WBT-USG" Name="usage_statistics_webtalk.html"/>
  <FileSet Name="sources" Type="DesignSrcs" RelSrcDir="$PSRCDIR/sources_1" RelGenDir="$PGENDIR/sources_1">
    <Filter Type="Srcs"/>
    <File Path="$PPRDIR/RTL/conv_sgnmag.sv">
      <FileInfo>
        <Attr Name="UsedIn" Val="synthesis"/>
        <Attr Name="UsedIn" Val="implementation"/>
        <Attr Name="UsedIn" Val="simulation"/>
      </FileInfo>
    </File>
    <File Path="$PPRDIR/RTL/count_3bit.sv">
      <FileInfo>
        <Attr Name="UsedIn" Val="synthesis"/>
        <Attr Name="UsedIn" Val="implementation"/>
        <Attr Name="UsedIn" Val="simulation"/>
      </FileInfo>
    </File>
    <File Path="$PPRDIR/RTL/dbl_dabble_ext.sv">
      <FileInfo>
        <Attr Name="UsedIn" Val="synthesis"/>
        <Attr Name="UsedIn" Val="implementation"/>
        <Attr Name="UsedIn" Val="simulation"/>
      </FileInfo>
    </File>
    <File Path="$PPRDIR/RTL/dec_3_8_n.sv">
      <FileInfo>
        <Attr Name="UsedIn" Val="synthesis"/>
        <Attr Name="UsedIn" Val="implementation"/>
        <Attr Name="UsedIn" Val="simulation"/>
      </FileInfo>
    </File>
    <File Path="$PPRDIR/RTL/mux8.sv">
      <FileInfo>
        <Attr Name="UsedIn" Val="synthesis"/>
        <Attr Name="UsedIn" Val="implementation"/>
        <Attr Name="UsedIn" Val="simulation"/>
      </FileInfo>
    </File>
    <File Path="$PPRDIR/RTL/period_enb.sv">
      <FileInfo>
        <Attr Name="UsedIn" Val="synthesis"/>
        <Attr Name="UsedIn" Val="implementation"/>
        <Attr Name="UsedIn" Val="simulation"/>
      </FileInfo>
    </File>
    <File Path="$PPRDIR/RTL/round.sv">
      <FileInfo>
        <Attr Name="UsedIn" Val="synthesis"/>
        <Attr Name="UsedIn" Val="implementation"/>
        <Attr Name="UsedIn" Val="simulation"/>
      </FileInfo>
    </File>
    <File Path="$PPRDIR/RTL/seven_seg_n.sv">
      <FileInfo>
        <Attr Name="UsedIn" Val="synthesis"/>
        <Attr Name="UsedIn" Val="implementation"/>
        <Attr Name="UsedIn" Val="simulation"/>
      </FileInfo>
    </File>
    <File Path="$PPRDIR/RTL/sevenseg_control.sv">
      <FileInfo>
        <Attr Name="UsedIn" Val="synthesis"/>
        <Attr Name="UsedIn" Val="implementation"/>
        <Attr Name="UsedIn" Val="simulation"/>
      </FileInfo>
    </File>
    <File Path="$PPRDIR/RTL/tconvert.sv">
      <FileInfo>
        <Attr Name="UsedIn" Val="synthesis"/>
        <Attr Name="UsedIn" Val="implementation"/>
        <Attr Name="UsedIn" Val="simulation"/>
      </FileInfo>
    </File>
    <File Path="$PPRDIR/RTL/TWICtl.vhd">
      <FileInfo>
        <Attr Name="UsedIn" Val="synthesis"/>
        <Attr Name="UsedIn" Val="simulation"/>
      </FileInfo>
    </File>
    <File Path="$PPRDIR/RTL/TempSensorCtl.vhd">
      <FileInfo>
        <Attr Name="UsedIn" Val="synthesis"/>
        <Attr Name="UsedIn" Val="simulation"/>
      </FileInfo>
    </File>
    <File Path="$PPRDIR/RTL/temp_top.sv">
      <FileInfo>
        <Attr Name="UsedIn" Val="synthesis"/>
        <Attr Name="UsedIn" Val="implementation"/>
        <Attr Name="UsedIn" Val="simulation"/>
      </FileInfo>
    </File>
    <Config>
      <Option Name="DesignMode" Val="RTL"/>
      <Option Name="TopModule" Val="temp_top"/>
    </Config>
  </FileSet>
  <FileSet Name="constrs_in" Type="Constrs" RelSrcDir="$PSRCDIR/constrs_1">
    <Filter Type="Constrs"/>
    <File Path="$PPRDIR/../Constraints/temp_con.xdc">
      <FileInfo>
        <Attr Name="UsedIn" Val="synthesis"/>
        <Attr Name="UsedIn" Val="implementation"/>
      </FileInfo>
    </File>
    <Config>
      <Option Name="ConstrsType" Val="XDC"/>
    </Config>
  </FileSet>
  <FileSet Name="utils" Type="Utils" RelSrcDir="$PSRCDIR/utils_1">
    <Filter Type="Utils"/>
    <Config>
      <Option Name="TopAutoSet" Val="TRUE"/>
    </Config>
  </FileSet>
  <Strategy Version="1" Minor="2">
    <StratHandle Name="Vivado Implementation Defaults" Flow="Vivado Implementation 2020"/>
    <Step Id="init_design"/>
    <Step Id="opt_design"/>
    <Step Id="power_opt_design"/>
    <Step Id="place_design"/>
    <Step Id="post_place_power_opt_design"/>
    <Step Id="phys_opt_design"/>
    <Step Id="route_design"/>
    <Step Id="post_route_phys_opt_design"/>
    <Step Id="write_bitstream"/>
  </Strategy>
</GenRun>
